educelab/cmdparse/__init__.py
educelab/cmdparse/cmdparse.py
educelab_cmdparse-0.2.0.dist-info/LICENSE
educelab_cmdparse-0.2.0.dist-info/METADATA
educelab_cmdparse-0.2.0.dist-info/WHEEL
educelab_cmdparse-0.2.0.dist-info/top_level.txt
educelab_cmdparse-0.2.0.dist-info/RECORD
